emotion.py
emotion_nrc_affect_lex-0.0.4.dist-info/LICENSE.txt
emotion_nrc_affect_lex-0.0.4.dist-info/METADATA
emotion_nrc_affect_lex-0.0.4.dist-info/WHEEL
emotion_nrc_affect_lex-0.0.4.dist-info/top_level.txt
emotion_nrc_affect_lex-0.0.4.dist-info/RECORD
