Metadata-Version: 2.1
Name: emotion-nrc-affect-lex
Version: 0.0.4
Summary: find emotion scores from a list of words
Home-page: https://github.com/tazwar2700/Emotion_NRC_affect_lexicon
Author: Syed Mahir Tazwar
Author-email: tazwar2700@gmail.com
License: UNKNOWN
Platform: UNKNOWN
Classifier: Programming Language :: Python :: 3
Classifier: Programming Language :: Python :: 3.6
Classifier: Programming Language :: Python :: 3.7
Classifier: License :: OSI Approved :: GNU General Public License v3 or later (GPLv3+)
Classifier: Operating System :: OS Independent
